pyyaledoorman/__init__.py
pyyaledoorman/client.py
pyyaledoorman/const.py
pyyaledoorman/device.py
pyyaledoorman/py.typed
pyyaledoorman-1.0.9.dist-info/LICENSE.rst
pyyaledoorman-1.0.9.dist-info/WHEEL
pyyaledoorman-1.0.9.dist-info/METADATA
pyyaledoorman-1.0.9.dist-info/RECORD
