Metadata-Version: 2.1
Name: pyyaledoorman
Version: 1.0.9
Summary: Python library for the Yale Doorman Smart API
Home-page: https://github.com/espenfjo/pyyaledoorman
License: MIT
Author: Espen Fjellvær Olsen
Author-email: espen@mrfjo.org
Requires-Python: >=3.9.0,<4.0.0
Classifier: License :: OSI Approved :: MIT License
Classifier: Programming Language :: Python :: 3
Classifier: Programming Language :: Python :: 3.10
Classifier: Programming Language :: Python :: 3.9
Requires-Dist: aiohttp (>=3.7.4,<4.0.0)
Requires-Dist: traitlets (>=5.0.5,<6.0.0)
Project-URL: Changelog, https://github.com/espenfjo/pyyaledoorman/releases
Project-URL: Documentation, https://pyyaledoorman.readthedocs.io
Project-URL: Repository, https://github.com/espenfjo/pyyaledoorman
